recallai/__init__.py
recallai-0.0.1.dist-info/METADATA
recallai-0.0.1.dist-info/WHEEL
recallai-0.0.1.dist-info/top_level.txt
recallai-0.0.1.dist-info/RECORD
