Metadata-Version: 2.1
Name: recallai
Version: 0.0.1
Summary: recall.ai Python SDK
Home-page: https://github.com/recall-ai/recallai-python
Author: Recall.ai
Author-email: hello@recall.ai
License: MIT
Platform: UNKNOWN
Classifier: License :: OSI Approved :: MIT License
Classifier: Programming Language :: Python :: 3
Classifier: Programming Language :: Python :: 3.7
